student90001/__init__.py
student90001/student90001.py
student90001-1.0.dist-info/METADATA
student90001-1.0.dist-info/WHEEL
student90001-1.0.dist-info/top_level.txt
student90001-1.0.dist-info/RECORD
